changes.txt
setup.py
ore/__init__.py
ore.yuiwidget.egg-info/PKG-INFO
ore.yuiwidget.egg-info/SOURCES.txt
ore.yuiwidget.egg-info/dependency_links.txt
ore.yuiwidget.egg-info/namespace_packages.txt
ore.yuiwidget.egg-info/not-zip-safe
ore.yuiwidget.egg-info/requires.txt
ore.yuiwidget.egg-info/top_level.txt
ore/yuiwidget/README.txt
ore/yuiwidget/__init__.py
ore/yuiwidget/autocomplete.py
ore/yuiwidget/calendar.py
ore/yuiwidget/configure.zcml
ore/yuiwidget/i18n.py
ore/yuiwidget/interfaces.py
ore/yuiwidget/richtext.py
ore/yuiwidget/tab.py
ore/yuiwidget/table.py
ore/yuiwidget/xss.py
ore/yuiwidget/resources/calbtn.gif