Metadata-Version: 1.0
Name: ore.yuiwidget
Version: 0.3.0
Summary: Zope3 Widgets From YUI
Home-page: http://pypi.python.org/pypi/ore.yui
Author: Kapil Thangavelu
Author-email: kapil.foss@gmail.com
License: ZPL
Platform: UNKNOWN
Classifier: Programming Language :: Python
Classifier: Environment :: Web Environment
Classifier: Topic :: Internet :: WWW/HTTP :: WSGI :: Application
Classifier: Framework :: Zope3
